hypotest_python3_sdk/__init__.py
hypotest_python3_sdk/config.py
hypotest_python3_sdk/experiment_settings.py
hypotest_python3_sdk/ht_connector.py
hypotest_python3_sdk/hypotest.py
hypotest_python3_sdk/logger.py
hypotest_python3_sdk/pymmh3.py
hypotest_python3_sdk/retrieve_experiments.py
hypotest_python3_sdk/routing.py
hypotest_python3_sdk/send_events.py
hypotest_python3_sdk/utils.py
hypotest_python3_sdk/variant.py
hypotest_python3_sdk-1.0.9.dist-info/LICENSE
hypotest_python3_sdk-1.0.9.dist-info/WHEEL
hypotest_python3_sdk-1.0.9.dist-info/METADATA
hypotest_python3_sdk-1.0.9.dist-info/RECORD
