Metadata-Version: 2.1
Name: hypotest-python3-sdk
Version: 1.0.9
Summary: 
Home-page: https://github.com/HypoTest-io/hypotest-python3-sdk
License: Apache-2.0 License
Keywords: ab testing,experiment,platform experimentation
Author: lior brafman
Author-email: liorb87@gmail.com
Maintainer: Lior Brafman
Maintainer-email: liorb87@gmail.com
Requires-Python: >=3.4,<4.0
Classifier: License :: Other/Proprietary License
Classifier: Programming Language :: Python :: 3
Classifier: Programming Language :: Python :: 3.10
Classifier: Programming Language :: Python :: 3.4
Classifier: Programming Language :: Python :: 3.5
Classifier: Programming Language :: Python :: 3.6
Classifier: Programming Language :: Python :: 3.7
Classifier: Programming Language :: Python :: 3.8
Classifier: Programming Language :: Python :: 3.9
Requires-Dist: PyJWT (>=2.3.0,<3.0.0)
Requires-Dist: pip-licenses (>=3.5.3,<4.0.0)
Requires-Dist: requests (>=2.27.1,<3.0.0)
Project-URL: Documentation, https://github.com/HypoTest-io/hypotest-python3-sdk
Project-URL: Repository, https://github.com/HypoTest-io/hypotest-python3-sdk
